{
  "portfolio.button.changelang": "Bahasa",
  "portfolio.metadata.description": "Portofolio saya",
  "portfolio.banner.title": "RYAN NGUYEN",
  "portfolio.banner.job": "PENGEMBANG FULL STACK",
  "portfolio.skills": "KETERAMPILAN",
  "portfolio.languages": "BAHASA",
  "portfolio.aboutme.name": "TENTANG SAYA",
  "portfolio.aboutme.details": "Dengan pengalaman 5 tahun sebagai Pengembang Frontend (HTML, CSS, JS, ReactJS) dan tambahan 3 tahun di Pengembangan Backend, saya memiliki keterampilan yang kuat yang menjembatani kedua aspek pengembangan web.",
  "portfolio.workexp": "PENGALAMAN KERJA",
  "portfolio.workexp.phase1.place": "HANOI UNIVERSITY",
  "portfolio.workexp.phase1.name": "PENGEMBANG FRONTEND",
  "portfolio.workexp.phase1.details.1": "Mahir dalam MERN stack yang diperoleh melalui proyek-proyek universitas secara langsung.",
  "portfolio.workexp.phase1.details.2": "Mengembangkan aplikasi Web3 inovatif menggunakan Solidity sebagai Pengembang Full Stack dalam proyek akhir.",
  "portfolio.workexp.phase2.name": "MAGANG",
  "portfolio.workexp.phase2.details.1": "Mengkoding frontend untuk website: https://nft-app.trava.finance",
  "portfolio.workexp.phase2.details.2": "Membuat frontend untuk banyak proyek outsource menggunakan NextJS.",
  "portfolio.workexp.phase2.details.3": "Membuat server untuk mengumpulkan data dari blockchain.",
  "portfolio.workexp.phase3.name": "PENGEMBANG BACKEND",
  "portfolio.workexp.phase3.details.1": "Memimpin pengembangan backend menggunakan framework ASP.NET untuk proyek berskala besar dengan dampak tinggi, memastikan performa dan skalabilitas yang kuat.",
  "portfolio.workexp.phase3.details.2": "Merancang dan mengimplementasikan database SQL Server untuk mengoptimalkan pengelolaan dan integritas data.",
  "portfolio.education.name": "PENDIDIKAN",
  "portfolio.education.phase1.place": "Universitas Ilmu Pengetahuan dan Teknologi Hanoi",
  "portfolio.education.phase1.title": "SARJANA",
  "portfolio.education.phase1.details.1": "Lulus dengan gelar sangat baik dalam Teknik Teknologi Informasi.",
  "portfolio.other": "LAINNYA"
}
